Workbook

Sheet Summary
A1: LDB FINANCE
A2: Advanced Micro Devices (AMD)
A3: Scenario model: 2030 earning power, capitalised and discounted back four years · Inputs in blue can be changed; everything else recalculates.
A6: SCENARIOS
B7: Bear | C7: Base | D7: Bull
A8: Value ($ per share) | B8: =Model!B23 -> 128.2256 | C8: =Model!C23 -> 319.28705 | D8: =Model!D23 -> 591.23583
A9: Probability | B9: 0.25 | C9: 0.5 | D9: 0.25
A10: Probability-weighted value ($ per share) | C10: =SUMPRODUCT(B8:D8,B9:D9) -> 339.50888
A11: Price at writing ($) | C11: 552.72
A12: Weighted value against the price | C12: =C10/C11-1 -> -0.38574887
A14: SENSITIVITY
A15: Base case, repriced at | B15: Discount rate | C15: Value per share ($)
B16: 0.1 | C16: =(Model!$C$20/(1+B16)^Model!$C$13+Model!$C$14)/Model!$C$15 -> 342.73789
B17: 0.11 | C17: =(Model!$C$20/(1+B17)^Model!$C$13+Model!$C$14)/Model!$C$15 -> 330.74842
B18: 0.12 | C18: =(Model!$C$20/(1+B18)^Model!$C$13+Model!$C$14)/Model!$C$15 -> 319.28705
B19: 0.13 | C19: =(Model!$C$20/(1+B19)^Model!$C$13+Model!$C$14)/Model!$C$15 -> 308.32612
B20: 0.14 | C20: =(Model!$C$20/(1+B20)^Model!$C$13+Model!$C$14)/Model!$C$15 -> 297.83964
A21: Each row reprices the base case at that discount rate.
A23: ABOUT THIS WORKBOOK
A24: Blue cells are inputs; black cells are formulas; green cells link to another sheet. Change any blue cell and the whole model recalculates.
A25: Built from the model script https://github.com/ldiazbusquets/finance/blob/main/_source/models/new_coverage.py, and checked against it each time the file is made.
A26: For education only. Not investment advice.

Sheet Model
A1: LDB FINANCE
A2: Advanced Micro Devices (AMD)
A3: Bear, base and bull in one table, $ billions
A6: INPUTS
B7: Bear | C7: Base | D7: Bull
A8: Revenue in 2030 ($B) | B8: 100 | C8: 150 | D8: 200
A9: Operating margin in 2030 | B9: 0.22 | C9: 0.3 | D9: 0.35
A10: Tax rate | B10: 0.21 | C10: 0.21 | D10: 0.21 | E10: U.S. federal rate
A11: Exit multiple of after-tax operating profit | B11: 20 | C11: 25 | D11: 30
A12: Discount rate | B12: 0.12 | C12: 0.12 | D12: 0.12
A13: Years discounted | B13: 4 | C13: 4 | D13: 4
A14: Net cash ($B) | B14: 9.9 | C14: 9.9 | D14: 9.9
A15: Shares by 2030 (billions) | B15: 1.8 | C15: 1.8 | D15: 1.8
A17: VALUE
B18: Bear | C18: Base | D18: Bull
A19: After-tax operating profit, 2030 ($B) | B19: =B8*B9*(1-B10) -> 17.38 | C19: =C8*C9*(1-C10) -> 35.55 | D19: =D8*D9*(1-D10) -> 55.3
A20: Value in 2030 ($B) | B20: =B19*B11 -> 347.6 | C20: =C19*C11 -> 888.75 | D20: =D19*D11 -> 1659
A21: Value today ($B) | B21: =B20/(1+B12)^B13 -> 220.90608 | C21: =C20/(1+C12)^C13 -> 564.81669 | D21: =D20/(1+D12)^D13 -> 1054.3245
A22: Plus net cash: equity value ($B) | B22: =B21+B14 -> 230.80608 | C22: =C21+C14 -> 574.71669 | D22: =D21+D14 -> 1064.2245
A23: Value per share ($) | B23: =B22/B15 -> 128.2256 | C23: =C22/C15 -> 319.28705 | D23: =D22/D15 -> 591.23583
