Workbook

Sheet Summary
A1: LDB FINANCE
A2: American Water Works (AWK)
A3: Dividend discount model · Inputs in blue can be changed; everything else recalculates.
A6: COST OF EQUITY (CAPM)
A7: Risk-free rate (10-year Treasury) | B7: 0.0515 | E7: FRED, October 2026
A8: Equity risk premium | B8: 0.045 | E8: Long-run U.S. premium
A9: Beta | B9: 0.7 | E9: Measured against the S&P 500
A10: Cost of equity | B10: =B7+B9*B8 -> 0.083
A12: SCENARIOS
B13: Bear | C13: Base | D13: Bull
A14: Value ($ per share) | B14: =Bear!$B$25 -> 69.369468 | C14: =Base!$B$25 -> 100.40245 | D14: =Bull!$B$25 -> 131.99137
A15: Probability | B15: 0.25 | C15: 0.5 | D15: 0.25
A16: Probability-weighted value ($ per share) | C16: =SUMPRODUCT(B14:D14,B15:D15) -> 100.54144
A17: Price at writing ($) | C17: 135.79
A18: Weighted value against the price | C18: =C16/C17-1 -> -0.25958144
A20: SENSITIVITY
A21: Base case, repriced at | B21: Cost of equity | C21: Value per share ($)
B22: 0.07 | C22: =SUMPRODUCT(Base!$B$17:$K$17,1/(1+B22)^Base!$B$15:$K$15)+Base!$K$17*(1+Base!$B$9)/(B22-Base!$B$9)/(1+B22)^10 -> 138.92675
B23: 0.075 | C23: =SUMPRODUCT(Base!$B$17:$K$17,1/(1+B23)^Base!$B$15:$K$15)+Base!$K$17*(1+Base!$B$9)/(B23-Base!$B$9)/(1+B23)^10 -> 121.13747
B24: 0.08 | C24: =SUMPRODUCT(Base!$B$17:$K$17,1/(1+B24)^Base!$B$15:$K$15)+Base!$K$17*(1+Base!$B$9)/(B24-Base!$B$9)/(1+B24)^10 -> 107.31124
B25: 0.085 | C25: =SUMPRODUCT(Base!$B$17:$K$17,1/(1+B25)^Base!$B$15:$K$15)+Base!$K$17*(1+Base!$B$9)/(B25-Base!$B$9)/(1+B25)^10 -> 96.258865
B26: 0.09 | C26: =SUMPRODUCT(Base!$B$17:$K$17,1/(1+B26)^Base!$B$15:$K$15)+Base!$K$17*(1+Base!$B$9)/(B26-Base!$B$9)/(1+B26)^10 -> 87.223569
A27: Each row reprices the base case at that cost of equity.
A29: ABOUT THIS WORKBOOK
A30: Blue cells are inputs; black cells are formulas; green cells link to another sheet. Change any blue cell and the whole model recalculates.
A31: Built from the model script https://github.com/ldiazbusquets/finance/blob/main/_source/models/awk.py, and checked against it each time the file is made.
A32: For education only. Not investment advice.

Sheet Base
A1: LDB FINANCE
A2: American Water Works (AWK)
A3: Base case: dividends per share, $
A6: INPUTS
A7: Dividend, last 12 months ($) | B7: 3.58 | C7: Company filings
A8: Dividend growth, years 1-5 | B8: 0.08 | C8: Company 7-9% EPS and dividend target
A9: Long-run growth, from year 10 | B9: 0.035 | C9: Growth fades to it over years 6-10
A10: Cost of equity shift for this case | B10: 0
A11: Cost of equity | B11: =Summary!$B$10+B10 -> 0.083
A13: DIVIDENDS
A14: Year | B14: 2027 | C14: 2028 | D14: 2029 | E14: 2030 | F14: 2031 | G14: 2032 | H14: 2033 | I14: 2034 | J14: 2035 | K14: 2036
A15: Year number | B15: 1 | C15: 2 | D15: 3 | E15: 4 | F15: 5 | G15: 6 | H15: 7 | I15: 8 | J15: 9 | K15: 10
A16: Dividend growth | B16: =$B$8 -> 0.08 | C16: =$B$8 -> 0.08 | D16: =$B$8 -> 0.08 | E16: =$B$8 -> 0.08 | F16: =$B$8 -> 0.08 | G16: =$B$8+($B$9-$B$8)*(G15-5)/5 -> 0.071 | H16: =$B$8+($B$9-$B$8)*(H15-5)/5 -> 0.062 | I16: =$B$8+($B$9-$B$8)*(I15-5)/5 -> 0.053 | J16: =$B$8+($B$9-$B$8)*(J15-5)/5 -> 0.044 | K16: =$B$8+($B$9-$B$8)*(K15-5)/5 -> 0.035
A17: Dividend per share ($) | B17: =$B$7*(1+B16) -> 3.8664 | C17: =B17*(1+C16) -> 4.175712 | D17: =C17*(1+D16) -> 4.509769 | E17: =D17*(1+E16) -> 4.8705505 | F17: =E17*(1+F16) -> 5.2601945 | G17: =F17*(1+G16) -> 5.6336683 | H17: =G17*(1+H16) -> 5.9829558 | I17: =H17*(1+I16) -> 6.3000524 | J17: =I17*(1+J16) -> 6.5772547 | K17: =J17*(1+K16) -> 6.8074586
A18: Discount factor | B18: =1/(1+$B$11)^B15 -> 0.92336103 | C18: =1/(1+$B$11)^C15 -> 0.8525956 | D18: =1/(1+$B$11)^D15 -> 0.78725355 | E18: =1/(1+$B$11)^E15 -> 0.72691926 | F18: =1/(1+$B$11)^F15 -> 0.67120892 | G18: =1/(1+$B$11)^G15 -> 0.61976816 | H18: =1/(1+$B$11)^H15 -> 0.57226977 | I18: =1/(1+$B$11)^I15 -> 0.5284116 | ... K18: =1/(1+$B$11)^K15 -> 0.45052141
A19: Present value ($) | B19: =B17*B18 -> 3.5700831 | C19: =C17*C18 -> 3.5601937 | D19: =D17*D18 -> 3.5503316 | E19: =E17*E18 -> 3.5404969 | F19: =F17*F18 -> 3.5306895 | G19: =G17*G18 -> 3.4915682 | H19: =H17*H18 -> 3.4238647 | I19: =I17*I18 -> 3.3290208 | ... K19: =K17*K18 -> 3.0669059
A21: VALUE PER SHARE
A22: Present value of ten years of dividends ($) | B22: =SUM(B19:K19) -> 34.272294
A23: Terminal value ($) | B23: =K17*(1+$B$9)/($B$11-$B$9) -> 146.78583 | C23: D10 x (1 + g) / (cost of equity - g)
A24: Present value of terminal value ($) | B24: =B23/(1+$B$11)^10 -> 66.130158
A25: Value per share ($) | B25: =B22+B24 -> 100.40245

Sheet Bear
A1: LDB FINANCE
A2: American Water Works (AWK)
A3: Bear case: dividends per share, $
A6: INPUTS
A7: Dividend, last 12 months ($) | B7: 3.58 | C7: Company filings
A8: Dividend growth, years 1-5 | B8: 0.06 | C8: Company 7-9% EPS and dividend target
A9: Long-run growth, from year 10 | B9: 0.03 | C9: Growth fades to it over years 6-10
A10: Cost of equity shift for this case | B10: 0.01
A11: Cost of equity | B11: =Summary!$B$10+B10 -> 0.093
A13: DIVIDENDS
A14: Year | B14: 2027 | C14: 2028 | D14: 2029 | E14: 2030 | F14: 2031 | G14: 2032 | H14: 2033 | I14: 2034 | J14: 2035 | K14: 2036
A15: Year number | B15: 1 | C15: 2 | D15: 3 | E15: 4 | F15: 5 | G15: 6 | H15: 7 | I15: 8 | J15: 9 | K15: 10
A16: Dividend growth | B16: =$B$8 -> 0.06 | C16: =$B$8 -> 0.06 | D16: =$B$8 -> 0.06 | E16: =$B$8 -> 0.06 | F16: =$B$8 -> 0.06 | G16: =$B$8+($B$9-$B$8)*(G15-5)/5 -> 0.054 | H16: =$B$8+($B$9-$B$8)*(H15-5)/5 -> 0.048 | I16: =$B$8+($B$9-$B$8)*(I15-5)/5 -> 0.042 | J16: =$B$8+($B$9-$B$8)*(J15-5)/5 -> 0.036 | K16: =$B$8+($B$9-$B$8)*(K15-5)/5 -> 0.03
A17: Dividend per share ($) | B17: =$B$7*(1+B16) -> 3.7948 | C17: =B17*(1+C16) -> 4.022488 | D17: =C17*(1+D16) -> 4.2638373 | E17: =D17*(1+E16) -> 4.5196675 | F17: =E17*(1+F16) -> 4.7908476 | G17: =F17*(1+G16) -> 5.0495533 | H17: =G17*(1+H16) -> 5.2919319 | I17: =H17*(1+I16) -> 5.514193 | J17: =I17*(1+J16) -> 5.712704 | K17: =J17*(1+K16) -> 5.8840851
A18: Discount factor | B18: =1/(1+$B$11)^B15 -> 0.91491308 | C18: =1/(1+$B$11)^C15 -> 0.83706595 | D18: =1/(1+$B$11)^D15 -> 0.76584259 | E18: =1/(1+$B$11)^E15 -> 0.7006794 | F18: =1/(1+$B$11)^F15 -> 0.64106075 | G18: =1/(1+$B$11)^G15 -> 0.58651487 | H18: =1/(1+$B$11)^H15 -> 0.53661013 | I18: =1/(1+$B$11)^I15 -> 0.49095163 | ... K18: =1/(1+$B$11)^K15 -> 0.41095889
A19: Present value ($) | B19: =B17*B18 -> 3.4719122 | C19: =C17*C18 -> 3.3670877 | D19: =D17*D18 -> 3.2654282 | E19: =E17*E18 -> 3.1668379 | F19: =F17*F18 -> 3.0712244 | G19: =G17*G18 -> 2.9616381 | H19: =H17*H18 -> 2.8397043 | I19: =I17*I18 -> 2.707202 | ... K19: =K17*K18 -> 2.4181171
A21: VALUE PER SHARE
A22: Present value of ten years of dividends ($) | B22: =SUM(B19:K19) -> 29.835173
A23: Terminal value ($) | B23: =K17*(1+$B$9)/($B$11-$B$9) -> 96.200122 | C23: D10 x (1 + g) / (cost of equity - g)
A24: Present value of terminal value ($) | B24: =B23/(1+$B$11)^10 -> 39.534295
A25: Value per share ($) | B25: =B22+B24 -> 69.369468

Sheet Bull
A1: LDB FINANCE
A2: American Water Works (AWK)
A3: Bull case: dividends per share, $
A6: INPUTS
A7: Dividend, last 12 months ($) | B7: 3.58 | C7: Company filings
A8: Dividend growth, years 1-5 | B8: 0.09 | C8: Company 7-9% EPS and dividend target
A9: Long-run growth, from year 10 | B9: 0.04 | C9: Growth fades to it over years 6-10
A10: Cost of equity shift for this case | B10: -0.005
A11: Cost of equity | B11: =Summary!$B$10+B10 -> 0.078
A13: DIVIDENDS
A14: Year | B14: 2027 | C14: 2028 | D14: 2029 | E14: 2030 | F14: 2031 | G14: 2032 | H14: 2033 | I14: 2034 | J14: 2035 | K14: 2036
A15: Year number | B15: 1 | C15: 2 | D15: 3 | E15: 4 | F15: 5 | G15: 6 | H15: 7 | I15: 8 | J15: 9 | K15: 10
A16: Dividend growth | B16: =$B$8 -> 0.09 | C16: =$B$8 -> 0.09 | D16: =$B$8 -> 0.09 | E16: =$B$8 -> 0.09 | F16: =$B$8 -> 0.09 | G16: =$B$8+($B$9-$B$8)*(G15-5)/5 -> 0.08 | H16: =$B$8+($B$9-$B$8)*(H15-5)/5 -> 0.07 | I16: =$B$8+($B$9-$B$8)*(I15-5)/5 -> 0.06 | J16: =$B$8+($B$9-$B$8)*(J15-5)/5 -> 0.05 | K16: =$B$8+($B$9-$B$8)*(K15-5)/5 -> 0.04
A17: Dividend per share ($) | B17: =$B$7*(1+B16) -> 3.9022 | C17: =B17*(1+C16) -> 4.253398 | D17: =C17*(1+D16) -> 4.6362038 | E17: =D17*(1+E16) -> 5.0534622 | F17: =E17*(1+F16) -> 5.5082738 | G17: =F17*(1+G16) -> 5.9489357 | H17: =G17*(1+H16) -> 6.3653612 | I17: =H17*(1+I16) -> 6.7472828 | J17: =I17*(1+J16) -> 7.084647 | K17: =J17*(1+K16) -> 7.3680328
A18: Discount factor | B18: =1/(1+$B$11)^B15 -> 0.92764378 | C18: =1/(1+$B$11)^C15 -> 0.86052299 | D18: =1/(1+$B$11)^D15 -> 0.7982588 | E18: =1/(1+$B$11)^E15 -> 0.74049982 | F18: =1/(1+$B$11)^F15 -> 0.68692005 | G18: =1/(1+$B$11)^G15 -> 0.63721712 | H18: =1/(1+$B$11)^H15 -> 0.5911105 | I18: =1/(1+$B$11)^I15 -> 0.54833998 | ... K18: =1/(1+$B$11)^K15 -> 0.47185916
A19: Present value ($) | B19: =B17*B18 -> 3.6198516 | C19: =C17*C18 -> 3.6601468 | D19: =D17*D18 -> 3.7008905 | E19: =E17*E18 -> 3.7420878 | F19: =F17*F18 -> 3.7837437 | G19: =G17*G18 -> 3.7907636 | H19: =H17*H18 -> 3.7626318 | I19: =I17*I18 -> 3.6998049 | ... K19: =K17*K18 -> 3.4766738
A21: VALUE PER SHARE
A22: Present value of ten years of dividends ($) | B22: =SUM(B19:K19) -> 36.840301
A23: Terminal value ($) | B23: =K17*(1+$B$9)/($B$11-$B$9) -> 201.65143 | C23: D10 x (1 + g) / (cost of equity - g)
A24: Present value of terminal value ($) | B24: =B23/(1+$B$11)^10 -> 95.151072
A25: Value per share ($) | B25: =B22+B24 -> 131.99137
