Workbook

Sheet Summary
A1: LDB FINANCE
A2: Anthropic (private)
A3: Scenario model: 2030 earning power, capitalised and discounted back four years · Inputs in blue can be changed; everything else recalculates.
A6: SCENARIOS
B7: Bear | C7: Base | D7: Bull
A8: Value ($B, whole company) | B8: =Model!B21 -> 162.60662 | C8: =Model!C21 -> 846.9095 | D8: =Model!D21 -> 2032.5828
A9: Probability | B9: 0.25 | C9: 0.5 | D9: 0.25
A10: Probability-weighted value ($B, whole company) | C10: =SUMPRODUCT(B8:D8,B9:D9) -> 972.2521
A11: Price at writing ($B, latest valuation) | C11: 965
A12: Weighted value against the price | C12: =C10/C11-1 -> 0.0075151298
A14: SENSITIVITY
A15: Base case, repriced at | B15: Discount rate | C15: Value ($B)
B16: 0.13 | C16: =(Model!$C$19/(1+B16)^Model!$C$13+Model!$C$14) -> 908.47837
B17: 0.14 | C17: =(Model!$C$19/(1+B17)^Model!$C$13+Model!$C$14) -> 877.01891
B18: 0.15 | C18: =(Model!$C$19/(1+B18)^Model!$C$13+Model!$C$14) -> 846.9095
B19: 0.16 | C19: =(Model!$C$19/(1+B19)^Model!$C$13+Model!$C$14) -> 818.08119
B20: 0.17 | C20: =(Model!$C$19/(1+B20)^Model!$C$13+Model!$C$14) -> 790.46913
A21: Each row reprices the base case at that discount rate.
A23: ABOUT THIS WORKBOOK
A24: Blue cells are inputs; black cells are formulas; green cells link to another sheet. Change any blue cell and the whole model recalculates.
A25: Built from the model script https://github.com/ldiazbusquets/finance/blob/main/_source/models/new_coverage.py, and checked against it each time the file is made.
A26: For education only. Not investment advice.

Sheet Model
A1: LDB FINANCE
A2: Anthropic (private)
A3: Bear, base and bull in one table, $ billions
A6: INPUTS
B7: Bear | C7: Base | D7: Bull
A8: Revenue in 2030 ($B) | B8: 120 | C8: 250 | D8: 450
A9: Operating margin in 2030 | B9: 0.15 | C9: 0.3 | D9: 0.4
A10: Tax rate | B10: 0.21 | C10: 0.21 | D10: 0.21 | E10: U.S. federal rate
A11: Exit multiple of after-tax operating profit | B11: 20 | C11: 25 | D11: 25
A12: Discount rate | B12: 0.15 | C12: 0.15 | D12: 0.15
A13: Years discounted | B13: 4 | C13: 4 | D13: 4
A14: Net cash ($B) | B14: 0 | C14: 0 | D14: 0
A16: VALUE
B17: Bear | C17: Base | D17: Bull
A18: After-tax operating profit, 2030 ($B) | B18: =B8*B9*(1-B10) -> 14.22 | C18: =C8*C9*(1-C10) -> 59.25 | D18: =D8*D9*(1-D10) -> 142.2
A19: Value in 2030 ($B) | B19: =B18*B11 -> 284.4 | C19: =C18*C11 -> 1481.25 | D19: =D18*D11 -> 3555
A20: Value today ($B) | B20: =B19/(1+B12)^B13 -> 162.60662 | C20: =C19/(1+C12)^C13 -> 846.9095 | D20: =D19/(1+D12)^D13 -> 2032.5828
A21: Plus net cash: equity value ($B) | B21: =B20+B14 -> 162.60662 | C21: =C20+C14 -> 846.9095 | D21: =D20+D14 -> 2032.5828
