Workbook

Sheet Summary
A1: LDB FINANCE
A2: GE Vernova (GEV)
A3: Ten-year discounted cash flow on the company’s 2028 targets · Inputs in blue can be changed; everything else recalculates.
A6: SCENARIOS
B7: Bear | C7: Base | D7: Bull
A8: Value ($ per share) | B8: =Bear!$B$41 -> 271.63061 | C8: =Base!$B$41 -> 442.47715 | D8: =Bull!$B$41 -> 682.38401
A9: Probability | B9: 0.25 | C9: 0.5 | D9: 0.25
A10: Probability-weighted value ($ per share) | C10: =SUMPRODUCT(B8:D8,B9:D9) -> 459.74223
A11: Price at writing ($) | C11: 890.33
A12: Weighted value against the price | C12: =C10/C11-1 -> -0.48362716
A14: SENSITIVITY
A15: Base case, repriced at | B15: Discount rate | C15: Value per share ($)
B16: 0.085 | C16: =(SUMPRODUCT(Base!$B$30:$K$30,1/(1+B16)^(Base!$B$23:$K$23-0.5))+Base!$K$27*(1+Base!$B$10)*(1-Base!$B$15)*(1-Base!$B$10/Base!$B$16)/(B16-Base!$B$10)/(1+B16)^9.5+Base!$B$18)/Base!$B$19 -> 607.08179
B17: 0.09 | C17: =(SUMPRODUCT(Base!$B$30:$K$30,1/(1+B17)^(Base!$B$23:$K$23-0.5))+Base!$K$27*(1+Base!$B$10)*(1-Base!$B$15)*(1-Base!$B$10/Base!$B$16)/(B17-Base!$B$10)/(1+B17)^9.5+Base!$B$18)/Base!$B$19 -> 559.07601
B18: 0.095 | C18: =(SUMPRODUCT(Base!$B$30:$K$30,1/(1+B18)^(Base!$B$23:$K$23-0.5))+Base!$K$27*(1+Base!$B$10)*(1-Base!$B$15)*(1-Base!$B$10/Base!$B$16)/(B18-Base!$B$10)/(1+B18)^9.5+Base!$B$18)/Base!$B$19 -> 518.45264
B19: 0.1 | C19: =(SUMPRODUCT(Base!$B$30:$K$30,1/(1+B19)^(Base!$B$23:$K$23-0.5))+Base!$K$27*(1+Base!$B$10)*(1-Base!$B$15)*(1-Base!$B$10/Base!$B$16)/(B19-Base!$B$10)/(1+B19)^9.5+Base!$B$18)/Base!$B$19 -> 483.6309
B20: 0.107 | C20: =(SUMPRODUCT(Base!$B$30:$K$30,1/(1+B20)^(Base!$B$23:$K$23-0.5))+Base!$K$27*(1+Base!$B$10)*(1-Base!$B$15)*(1-Base!$B$10/Base!$B$16)/(B20-Base!$B$10)/(1+B20)^9.5+Base!$B$18)/Base!$B$19 -> 442.47715
A21: Each row reprices the base case at that discount rate; the cash flows themselves do not change.
A23: ABOUT THIS WORKBOOK
A24: Blue cells are inputs; black cells are formulas; green cells link to another sheet. Change any blue cell and the whole model recalculates.
A25: Built from the model script https://github.com/ldiazbusquets/finance/blob/main/_source/models/gev.py, and checked against it each time the file is made.
A26: For education only. Not investment advice.

Sheet Base
A1: LDB FINANCE
A2: GE Vernova (GEV)
A3: Base case: ten-year free cash flow to the firm, $ billions
A6: INPUTS
A7: Revenue, 2026 ($B) | B7: 46 | C7: Guidance
A8: Revenue growth, 2027 | B8: 0.12
A9: Revenue growth, 2028 | B9: 0.1 | C9: Then fades to terminal growth by 2036
A10: Terminal growth | B10: 0.03
A11: EBITDA margin, 2026 | B11: 0.13
A12: EBITDA margin, 2028 target | B12: 0.2 | C12: Company 2028 target, reached in two years
A13: Depreciation, share of revenue | B13: 0.022
A14: Sales to capital | B14: 4 | C14: Reinvestment = revenue growth / 4
A15: Tax rate | B15: 0.21
A16: Return on new capital, after year 10 | B16: 0.2
A17: Discount rate | B17: 0.107 | C17: CAPM with beta about 1.2; no net debt
A18: Net cash ($B) | B18: 10.27 | C18: Jun 30 2026: $13.12B cash less $2.85B debt
A19: Diluted shares (billions) | B19: 0.2663
A21: PROJECTION
A22: Year | B22: 2027 | C22: 2028 | D22: 2029 | E22: 2030 | F22: 2031 | G22: 2032 | H22: 2033 | I22: 2034 | J22: 2035 | K22: 2036
A23: Year number | B23: 1 | C23: 2 | D23: 3 | E23: 4 | F23: 5 | G23: 6 | H23: 7 | I23: 8 | J23: 9 | K23: 10
A24: Revenue growth | B24: =$B$8 -> 0.12 | C24: =$B$9 -> 0.1 | D24: =$B$9+($B$10-$B$9)*(D23-2)/8 -> 0.09125 | E24: =$B$9+($B$10-$B$9)*(E23-2)/8 -> 0.0825 | F24: =$B$9+($B$10-$B$9)*(F23-2)/8 -> 0.07375 | G24: =$B$9+($B$10-$B$9)*(G23-2)/8 -> 0.065 | H24: =$B$9+($B$10-$B$9)*(H23-2)/8 -> 0.05625 | I24: =$B$9+($B$10-$B$9)*(I23-2)/8 -> 0.0475 | J24: =$B$9+($B$10-$B$9)*(J23-2)/8 -> 0.03875 | K24: =$B$9+($B$10-$B$9)*(K23-2)/8 -> 0.03
A25: Revenue ($B) | B25: =$B$7*(1+B24) -> 51.52 | C25: =B25*(1+C24) -> 56.672 | D25: =C25*(1+D24) -> 61.84332 | E25: =D25*(1+E24) -> 66.945394 | F25: =E25*(1+F24) -> 71.882617 | G25: =F25*(1+G24) -> 76.554987 | H25: =G25*(1+H24) -> 80.861205 | I25: =H25*(1+I24) -> 84.702112 | J25: =I25*(1+J24) -> 87.984319 | K25: =J25*(1+K24) -> 90.623848
A26: EBITDA margin | B26: =$B$11+($B$12-$B$11)*MIN(1,B23/2) -> 0.165 | C26: =$B$11+($B$12-$B$11)*MIN(1,C23/2) -> 0.2 | D26: =$B$11+($B$12-$B$11)*MIN(1,D23/2) -> 0.2 | E26: =$B$11+($B$12-$B$11)*MIN(1,E23/2) -> 0.2 | F26: =$B$11+($B$12-$B$11)*MIN(1,F23/2) -> 0.2 | G26: =$B$11+($B$12-$B$11)*MIN(1,G23/2) -> 0.2 | H26: =$B$11+($B$12-$B$11)*MIN(1,H23/2) -> 0.2 | I26: =$B$11+($B$12-$B$11)*MIN(1,I23/2) -> 0.2 | ... K26: =$B$11+($B$12-$B$11)*MIN(1,K23/2) -> 0.2
A27: Operating income ($B) | B27: =B25*(B26-$B$13) -> 7.36736 | C27: =C25*(C26-$B$13) -> 10.087616 | D27: =D25*(D26-$B$13) -> 11.008111 | E27: =E25*(E26-$B$13) -> 11.91628 | F27: =F25*(F26-$B$13) -> 12.795106 | G27: =G25*(G26-$B$13) -> 13.626788 | H27: =H25*(H26-$B$13) -> 14.393294 | I27: =I25*(I26-$B$13) -> 15.076976 | ... K27: =K25*(K26-$B$13) -> 16.131045
A28: After-tax operating income ($B) | B28: =B27*(1-$B$15) -> 5.8202144 | C28: =C27*(1-$B$15) -> 7.9692166 | D28: =D27*(1-$B$15) -> 8.6964077 | E28: =E27*(1-$B$15) -> 9.4138613 | F28: =F27*(1-$B$15) -> 10.108134 | G28: =G27*(1-$B$15) -> 10.765162 | H28: =H27*(1-$B$15) -> 11.370703 | I28: =I27*(1-$B$15) -> 11.910811 | ... K28: =K27*(1-$B$15) -> 12.743526
A29: Reinvestment ($B) | B29: =(B25-$B$7)/$B$14 -> 1.38 | C29: =(C25-B25)/$B$14 -> 1.288 | D29: =(D25-C25)/$B$14 -> 1.29283 | E29: =(E25-D25)/$B$14 -> 1.2755185 | F29: =(F25-E25)/$B$14 -> 1.2343057 | G29: =(G25-F25)/$B$14 -> 1.1680925 | H29: =(H25-G25)/$B$14 -> 1.0765545 | I29: =(I25-H25)/$B$14 -> 0.96022681 | J29: =(J25-I25)/$B$14 -> 0.82055171 | K29: =(K25-J25)/$B$14 -> 0.65988239
A30: Free cash flow to the firm ($B) | B30: =B28-B29 -> 4.4402144 | C30: =C28-C29 -> 6.6812166 | D30: =D28-D29 -> 7.4035777 | E30: =E28-E29 -> 8.1383428 | F30: =F28-F29 -> 8.8738279 | G30: =G28-G29 -> 9.5970697 | H30: =H28-H29 -> 10.294148 | I30: =I28-I29 -> 10.950584 | ... K30: =K28-K29 -> 12.083643
A31: Discount factor (mid-year) | B31: =1/(1+$B$17)^(B23-0.5) -> 0.95044325 | C31: =1/(1+$B$17)^(C23-0.5) -> 0.85857565 | D31: =1/(1+$B$17)^(D23-0.5) -> 0.77558776 | E31: =1/(1+$B$17)^(E23-0.5) -> 0.70062128 | F31: =1/(1+$B$17)^(F23-0.5) -> 0.63290089 | G31: =1/(1+$B$17)^(G23-0.5) -> 0.57172619 | H31: =1/(1+$B$17)^(H23-0.5) -> 0.51646449 | I31: =1/(1+$B$17)^(I23-0.5) -> 0.46654425 | ... K31: =1/(1+$B$17)^(K23-0.5) -> 0.38071291
A32: Present value ($B) | B32: =B30*B31 -> 4.2201718 | C32: =C30*C31 -> 5.7363299 | D32: =D30*D31 -> 5.7421242 | E32: =E30*E31 -> 5.7018962 | F32: =F30*F31 -> 5.6162535 | G32: =G30*G31 -> 5.4868961 | H32: =H30*H31 -> 5.3165619 | I32: =I30*I31 -> 5.1089321 | ... K32: =K30*K31 -> 4.6003989
A34: BRIDGE TO VALUE PER SHARE
A35: Present value of ten years of cash flow ($B) | B35: =SUM(B32:K32) -> 52.398063
A36: Year-11 after-tax operating income ($B) | B36: =K27*(1+$B$10)*(1-$B$15) -> 13.125831
A37: Terminal value ($B) | B37: =B36*(1-$B$10/$B$16)/($B$17-$B$10) -> 144.89554 | C37: NOPAT11 x (1 - g / return on new capital) / (discount rate - g)
A38: Present value of terminal value ($B) | B38: =B37/(1+$B$17)^9.5 -> 55.163603
A39: Enterprise value ($B) | B39: =B35+B38 -> 107.56167
A40: Equity value ($B) | B40: =B39+$B$18 -> 117.83167
A41: Value per share ($) | B41: =B40/$B$19 -> 442.47715

Sheet Bear
A1: LDB FINANCE
A2: GE Vernova (GEV)
A3: Bear case: ten-year free cash flow to the firm, $ billions
A6: INPUTS
A7: Revenue, 2026 ($B) | B7: 46 | C7: Guidance
A8: Revenue growth, 2027 | B8: 0.07
A9: Revenue growth, 2028 | B9: 0.05 | C9: Then fades to terminal growth by 2036
A10: Terminal growth | B10: 0.03
A11: EBITDA margin, 2026 | B11: 0.13
A12: EBITDA margin, 2028 target | B12: 0.16 | C12: Company 2028 target, reached in two years
A13: Depreciation, share of revenue | B13: 0.022
A14: Sales to capital | B14: 4 | C14: Reinvestment = revenue growth / 4
A15: Tax rate | B15: 0.21
A16: Return on new capital, after year 10 | B16: 0.2
A17: Discount rate | B17: 0.115 | C17: CAPM with beta about 1.2; no net debt
A18: Net cash ($B) | B18: 10.27 | C18: Jun 30 2026: $13.12B cash less $2.85B debt
A19: Diluted shares (billions) | B19: 0.2663
A21: PROJECTION
A22: Year | B22: 2027 | C22: 2028 | D22: 2029 | E22: 2030 | F22: 2031 | G22: 2032 | H22: 2033 | I22: 2034 | J22: 2035 | K22: 2036
A23: Year number | B23: 1 | C23: 2 | D23: 3 | E23: 4 | F23: 5 | G23: 6 | H23: 7 | I23: 8 | J23: 9 | K23: 10
A24: Revenue growth | B24: =$B$8 -> 0.07 | C24: =$B$9 -> 0.05 | D24: =$B$9+($B$10-$B$9)*(D23-2)/8 -> 0.0475 | E24: =$B$9+($B$10-$B$9)*(E23-2)/8 -> 0.045 | F24: =$B$9+($B$10-$B$9)*(F23-2)/8 -> 0.0425 | G24: =$B$9+($B$10-$B$9)*(G23-2)/8 -> 0.04 | H24: =$B$9+($B$10-$B$9)*(H23-2)/8 -> 0.0375 | I24: =$B$9+($B$10-$B$9)*(I23-2)/8 -> 0.035 | J24: =$B$9+($B$10-$B$9)*(J23-2)/8 -> 0.0325 | K24: =$B$9+($B$10-$B$9)*(K23-2)/8 -> 0.03
A25: Revenue ($B) | B25: =$B$7*(1+B24) -> 49.22 | C25: =B25*(1+C24) -> 51.681 | D25: =C25*(1+D24) -> 54.135847 | E25: =D25*(1+E24) -> 56.571961 | F25: =E25*(1+F24) -> 58.976269 | G25: =F25*(1+G24) -> 61.33532 | H25: =G25*(1+H24) -> 63.635394 | I25: =H25*(1+I24) -> 65.862633 | J25: =I25*(1+J24) -> 68.003169 | K25: =J25*(1+K24) -> 70.043264
A26: EBITDA margin | B26: =$B$11+($B$12-$B$11)*MIN(1,B23/2) -> 0.145 | C26: =$B$11+($B$12-$B$11)*MIN(1,C23/2) -> 0.16 | D26: =$B$11+($B$12-$B$11)*MIN(1,D23/2) -> 0.16 | E26: =$B$11+($B$12-$B$11)*MIN(1,E23/2) -> 0.16 | F26: =$B$11+($B$12-$B$11)*MIN(1,F23/2) -> 0.16 | G26: =$B$11+($B$12-$B$11)*MIN(1,G23/2) -> 0.16 | H26: =$B$11+($B$12-$B$11)*MIN(1,H23/2) -> 0.16 | I26: =$B$11+($B$12-$B$11)*MIN(1,I23/2) -> 0.16 | ... K26: =$B$11+($B$12-$B$11)*MIN(1,K23/2) -> 0.16
A27: Operating income ($B) | B27: =B25*(B26-$B$13) -> 6.05406 | C27: =C25*(C26-$B$13) -> 7.131978 | D27: =D25*(D26-$B$13) -> 7.470747 | E27: =E25*(E26-$B$13) -> 7.8069306 | F27: =F25*(F26-$B$13) -> 8.1387251 | G27: =G25*(G26-$B$13) -> 8.4642741 | H27: =H25*(H26-$B$13) -> 8.7816844 | I27: =I25*(I26-$B$13) -> 9.0890434 | ... K27: =K25*(K26-$B$13) -> 9.6659704
A28: After-tax operating income ($B) | B28: =B27*(1-$B$15) -> 4.7827074 | C28: =C27*(1-$B$15) -> 5.6342626 | D28: =D27*(1-$B$15) -> 5.9018901 | E28: =E27*(1-$B$15) -> 6.1674751 | F28: =F27*(1-$B$15) -> 6.4295928 | G28: =G27*(1-$B$15) -> 6.6867766 | H28: =H27*(1-$B$15) -> 6.9375307 | I28: =I27*(1-$B$15) -> 7.1803443 | ... K28: =K27*(1-$B$15) -> 7.6361166
A29: Reinvestment ($B) | B29: =(B25-$B$7)/$B$14 -> 0.805 | C29: =(C25-B25)/$B$14 -> 0.61525 | D29: =(D25-C25)/$B$14 -> 0.61371188 | E29: =(E25-D25)/$B$14 -> 0.60902828 | F29: =(F25-E25)/$B$14 -> 0.60107708 | G29: =(G25-F25)/$B$14 -> 0.58976269 | H29: =(H25-G25)/$B$14 -> 0.57501862 | I29: =(I25-H25)/$B$14 -> 0.5568097 | J29: =(J25-I25)/$B$14 -> 0.53513389 | K29: =(K25-J25)/$B$14 -> 0.51002376
A30: Free cash flow to the firm ($B) | B30: =B28-B29 -> 3.9777074 | C30: =C28-C29 -> 5.0190126 | D30: =D28-D29 -> 5.2881782 | E30: =E28-E29 -> 5.5584469 | F30: =F28-F29 -> 5.8285158 | G30: =G28-G29 -> 6.0970139 | H30: =H28-H29 -> 6.3625121 | I30: =I28-I29 -> 6.6235346 | ... K30: =K28-K29 -> 7.1260928
A31: Discount factor (mid-year) | B31: =1/(1+$B$17)^(B23-0.5) -> 0.94702745 | C31: =1/(1+$B$17)^(C23-0.5) -> 0.84935197 | D31: =1/(1+$B$17)^(D23-0.5) -> 0.76175065 | E31: =1/(1+$B$17)^(E23-0.5) -> 0.68318444 | F31: =1/(1+$B$17)^(F23-0.5) -> 0.61272147 | G31: =1/(1+$B$17)^(G23-0.5) -> 0.54952598 | H31: =1/(1+$B$17)^(H23-0.5) -> 0.49284841 | I31: =1/(1+$B$17)^(I23-0.5) -> 0.44201651 | ... K31: =1/(1+$B$17)^(K23-0.5) -> 0.35554024
A32: Present value ($B) | B32: =B30*B31 -> 3.7669981 | C32: =C30*C31 -> 4.2629083 | D32: =D30*D31 -> 4.0282732 | E32: =E30*E31 -> 3.7974444 | F32: =F30*F31 -> 3.5712567 | G32: =G30*G31 -> 3.3504675 | H32: =H30*H31 -> 3.135754 | I32: =I30*I31 -> 2.9277116 | ... K32: =K30*K31 -> 2.5336127
A34: BRIDGE TO VALUE PER SHARE
A35: Present value of ten years of cash flow ($B) | B35: =SUM(B32:K32) -> 34.101281
A36: Year-11 after-tax operating income ($B) | B36: =K27*(1+$B$10)*(1-$B$15) -> 7.8652001
A37: Terminal value ($B) | B37: =B36*(1-$B$10/$B$16)/($B$17-$B$10) -> 78.652001 | C37: NOPAT11 x (1 - g / return on new capital) / (discount rate - g)
A38: Present value of terminal value ($B) | B38: =B37/(1+$B$17)^9.5 -> 27.963951
A39: Enterprise value ($B) | B39: =B35+B38 -> 62.065232
A40: Equity value ($B) | B40: =B39+$B$18 -> 72.335232
A41: Value per share ($) | B41: =B40/$B$19 -> 271.63061

Sheet Bull
A1: LDB FINANCE
A2: GE Vernova (GEV)
A3: Bull case: ten-year free cash flow to the firm, $ billions
A6: INPUTS
A7: Revenue, 2026 ($B) | B7: 46 | C7: Guidance
A8: Revenue growth, 2027 | B8: 0.16
A9: Revenue growth, 2028 | B9: 0.14 | C9: Then fades to terminal growth by 2036
A10: Terminal growth | B10: 0.03
A11: EBITDA margin, 2026 | B11: 0.13
A12: EBITDA margin, 2028 target | B12: 0.23 | C12: Company 2028 target, reached in two years
A13: Depreciation, share of revenue | B13: 0.022
A14: Sales to capital | B14: 4 | C14: Reinvestment = revenue growth / 4
A15: Tax rate | B15: 0.21
A16: Return on new capital, after year 10 | B16: 0.2
A17: Discount rate | B17: 0.097 | C17: CAPM with beta about 1.2; no net debt
A18: Net cash ($B) | B18: 10.27 | C18: Jun 30 2026: $13.12B cash less $2.85B debt
A19: Diluted shares (billions) | B19: 0.2663
A21: PROJECTION
A22: Year | B22: 2027 | C22: 2028 | D22: 2029 | E22: 2030 | F22: 2031 | G22: 2032 | H22: 2033 | I22: 2034 | J22: 2035 | K22: 2036
A23: Year number | B23: 1 | C23: 2 | D23: 3 | E23: 4 | F23: 5 | G23: 6 | H23: 7 | I23: 8 | J23: 9 | K23: 10
A24: Revenue growth | B24: =$B$8 -> 0.16 | C24: =$B$9 -> 0.14 | D24: =$B$9+($B$10-$B$9)*(D23-2)/8 -> 0.12625 | E24: =$B$9+($B$10-$B$9)*(E23-2)/8 -> 0.1125 | F24: =$B$9+($B$10-$B$9)*(F23-2)/8 -> 0.09875 | G24: =$B$9+($B$10-$B$9)*(G23-2)/8 -> 0.085 | H24: =$B$9+($B$10-$B$9)*(H23-2)/8 -> 0.07125 | I24: =$B$9+($B$10-$B$9)*(I23-2)/8 -> 0.0575 | J24: =$B$9+($B$10-$B$9)*(J23-2)/8 -> 0.04375 | K24: =$B$9+($B$10-$B$9)*(K23-2)/8 -> 0.03
A25: Revenue ($B) | B25: =$B$7*(1+B24) -> 53.36 | C25: =B25*(1+C24) -> 60.8304 | D25: =C25*(1+D24) -> 68.510238 | E25: =D25*(1+E24) -> 76.21764 | F25: =E25*(1+F24) -> 83.744132 | G25: =F25*(1+G24) -> 90.862383 | H25: =G25*(1+H24) -> 97.336328 | I25: =H25*(1+I24) -> 102.93317 | J25: =I25*(1+J24) -> 107.43649 | K25: =J25*(1+K24) -> 110.65959
A26: EBITDA margin | B26: =$B$11+($B$12-$B$11)*MIN(1,B23/2) -> 0.18 | C26: =$B$11+($B$12-$B$11)*MIN(1,C23/2) -> 0.23 | D26: =$B$11+($B$12-$B$11)*MIN(1,D23/2) -> 0.23 | E26: =$B$11+($B$12-$B$11)*MIN(1,E23/2) -> 0.23 | F26: =$B$11+($B$12-$B$11)*MIN(1,F23/2) -> 0.23 | G26: =$B$11+($B$12-$B$11)*MIN(1,G23/2) -> 0.23 | H26: =$B$11+($B$12-$B$11)*MIN(1,H23/2) -> 0.23 | I26: =$B$11+($B$12-$B$11)*MIN(1,I23/2) -> 0.23 | ... K26: =$B$11+($B$12-$B$11)*MIN(1,K23/2) -> 0.23
A27: Operating income ($B) | B27: =B25*(B26-$B$13) -> 8.43088 | C27: =C25*(C26-$B$13) -> 12.652723 | D27: =D25*(D26-$B$13) -> 14.25013 | E27: =E25*(E26-$B$13) -> 15.853269 | F27: =F25*(F26-$B$13) -> 17.418779 | G27: =G25*(G26-$B$13) -> 18.899376 | H27: =H25*(H26-$B$13) -> 20.245956 | I27: =I25*(I26-$B$13) -> 21.410099 | ... K27: =K25*(K26-$B$13) -> 23.017194
A28: After-tax operating income ($B) | B28: =B27*(1-$B$15) -> 6.6603952 | C28: =C27*(1-$B$15) -> 9.9956513 | D28: =D27*(1-$B$15) -> 11.257602 | E28: =E27*(1-$B$15) -> 12.524083 | F28: =F27*(1-$B$15) -> 13.760836 | G28: =G27*(1-$B$15) -> 14.930507 | H28: =H27*(1-$B$15) -> 15.994305 | I28: =I27*(1-$B$15) -> 16.913978 | ... K28: =K27*(1-$B$15) -> 18.183583
A29: Reinvestment ($B) | B29: =(B25-$B$7)/$B$14 -> 1.84 | C29: =(C25-B25)/$B$14 -> 1.8676 | D29: =(D25-C25)/$B$14 -> 1.9199595 | E29: =(E25-D25)/$B$14 -> 1.9268504 | F29: =(F25-E25)/$B$14 -> 1.881623 | G29: =(G25-F25)/$B$14 -> 1.7795628 | H29: =(H25-G25)/$B$14 -> 1.6184862 | I29: =(I25-H25)/$B$14 -> 1.3992097 | J29: =(J25-I25)/$B$14 -> 1.1258315 | K29: =(K25-J25)/$B$14 -> 0.80577369
A30: Free cash flow to the firm ($B) | B30: =B28-B29 -> 4.8203952 | C30: =C28-C29 -> 8.1280513 | D30: =D28-D29 -> 9.3376428 | E30: =E28-E29 -> 10.597232 | F30: =F28-F29 -> 11.879213 | G30: =G28-G29 -> 13.150944 | H30: =H28-H29 -> 14.375819 | I30: =I28-I29 -> 15.514768 | ... K30: =K28-K29 -> 17.37781
A31: Discount factor (mid-year) | B31: =1/(1+$B$17)^(B23-0.5) -> 0.95476543 | C31: =1/(1+$B$17)^(C23-0.5) -> 0.87034223 | D31: =1/(1+$B$17)^(D23-0.5) -> 0.79338399 | E31: =1/(1+$B$17)^(E23-0.5) -> 0.72323062 | F31: =1/(1+$B$17)^(F23-0.5) -> 0.65928042 | G31: =1/(1+$B$17)^(G23-0.5) -> 0.60098488 | H31: =1/(1+$B$17)^(H23-0.5) -> 0.54784401 | I31: =1/(1+$B$17)^(I23-0.5) -> 0.49940202 | ... K31: =1/(1+$B$17)^(K23-0.5) -> 0.41498943
A32: Present value ($B) | B32: =B30*B31 -> 4.6023467 | C32: =C30*C31 -> 7.0741864 | D32: =D30*D31 -> 7.4083363 | E32: =E30*E31 -> 7.6642427 | F32: =F30*F31 -> 7.8317323 | G32: =G30*G31 -> 7.9035185 | H32: =H30*H31 -> 7.8757065 | I32: =I30*I31 -> 7.7481066 | ... K32: =K30*K31 -> 7.2116074
A34: BRIDGE TO VALUE PER SHARE
A35: Present value of ten years of cash flow ($B) | B35: =SUM(B32:K32) -> 72.844107
A36: Year-11 after-tax operating income ($B) | B36: =K27*(1+$B$10)*(1-$B$15) -> 18.729091
A37: Terminal value ($B) | B37: =B36*(1-$B$10/$B$16)/($B$17-$B$10) -> 237.60787 | C37: NOPAT11 x (1 - g / return on new capital) / (discount rate - g)
A38: Present value of terminal value ($B) | B38: =B37/(1+$B$17)^9.5 -> 98.604755
A39: Enterprise value ($B) | B39: =B35+B38 -> 171.44886
A40: Equity value ($B) | B40: =B39+$B$18 -> 181.71886
A41: Value per share ($) | B41: =B40/$B$19 -> 682.38401
